README.md
setup.py
Margos.egg-info/PKG-INFO
Margos.egg-info/SOURCES.txt
Margos.egg-info/dependency_links.txt
Margos.egg-info/entry_points.txt
Margos.egg-info/requires.txt
Margos.egg-info/top_level.txt
margos/__init__.py
margos/display.py
margos/main.py
margos/models.py
margos/parsing.py
margos/system.py
margos/worker.py
margos/resources/__init__.py
margos/resources/applet.ini
margos/resources/dbus.ini
margos/resources/preferences_dialog.xml
margos/resources/schema.xml