Metadata-Version: 2.1
Name: Margos
Version: 0.0.2
Summary: Customize your Mate applets from your scripts' output
Home-page: https://github.com/ssimono/margos
Author: Simon Alfassa
Author-email: simon@sa-web.fr
License: MIT
Keywords: margos mate applet desktop argos bitbar linux
Platform: UNKNOWN
Requires-Python: >=3.6
Provides-Extra: dev
